LICENSE
README.md
setup.cfg
setup.py
TxGNN.egg-info/PKG-INFO
TxGNN.egg-info/SOURCES.txt
TxGNN.egg-info/dependency_links.txt
TxGNN.egg-info/not-zip-safe
TxGNN.egg-info/requires.txt
TxGNN.egg-info/top_level.txt
txgnn/TxData.py
txgnn/TxEval.py
txgnn/TxGNN.py
txgnn/__init__.py
txgnn/model.py
txgnn/utils.py
txgnn/version.py
txgnn/data_splits/__init__.py
txgnn/data_splits/datasplit.py
txgnn/data_splits/do_obo_parser.py
txgnn/graphmask/__init__.py
txgnn/graphmask/abstract_torch_module.py
txgnn/graphmask/hard_concrete.py
txgnn/graphmask/lagrangian_optimization.py
txgnn/graphmask/moving_average.py
txgnn/graphmask/multiple_inputs_layernorm_linear.py
txgnn/graphmask/sigmoid_penalty.py
txgnn/graphmask/squeezer.py