Metadata-Version: 2.1
Name: TxGNN
Version: 0.0.3
Summary: TxGNN
Home-page: https://github.com/mims-harvard/TxGNN
Author: TxGNN Team
Author-email: kexinh@stanford.edu
License: MIT
Platform: UNKNOWN
License-File: LICENSE
